{"nodes": [{"id": "backend_requirements_base", "label": "Backend Base Requirements (requirements-base.txt)", "file_type": "code", "source_file": "backend/requirements-base.txt", "source_location": null, "source_url": null, "captured_at": null, "author": null, "contributor": null}, {"id": "concept_django", "label": "Django 5.2 / 6.0 (web framework)", "file_type": "concept", "source_file": "backend/requirements-base.txt", "source_location": null, "source_url": null, "captured_at": null, "author": null, "contributor": null}, {"id": "concept_drf", "label": "Django REST Framework (DRF)", "file_type": "concept", "source_file": "backend/requirements-base.txt", "source_location": null, "source_url": null, "captured_at": null, "author": null, "contributor": null}, {"id": "concept_simplejwt", "label": "djangorestframework-simplejwt (JWT auth)", "file_type": "concept", "source_file": "backend/requirements-base.txt", "source_location": null, "source_url": null, "captured_at": null, "author": null, "contributor": null}, {"id": "concept_django_cors_headers", "label": "django-cors-headers (CORS handling)", "file_type": "concept", "source_file": "backend/requirements-base.txt", "source_location": null, "source_url": null, "captured_at": null, "author": null, "contributor": null}, {"id": "concept_celery", "label": "Celery 5.6 (async task queue)", "file_type": "concept", "source_file": "backend/requirements-base.txt", "source_location": null, "source_url": null, "captured_at": null, "author": null, "contributor": null}, {"id": "concept_redis", "label": "Redis 8 (cache + Celery broker)", "file_type": "concept", "source_file": "backend/requirements-base.txt", "source_location": null, "source_url": null, "captured_at": null, "author": null, "contributor": null}, {"id": "concept_gunicorn", "label": "Gunicorn (WSGI HTTP server)", "file_type": "concept", "source_file": "backend/requirements-base.txt", "source_location": null, "source_url": null, "captured_at": null, "author": null, "contributor": null}, {"id": "concept_uvicorn", "label": "Uvicorn 0.49 (ASGI HTTP server)", "file_type": "concept", "source_file": "backend/requirements-base.txt", "source_location": null, "source_url": null, "captured_at": null, "author": null, "contributor": null}, {"id": "concept_django_environ", "label": "django-environ (env config)", "file_type": "concept", "source_file": "backend/requirements-base.txt", "source_location": null, "source_url": null, "captured_at": null, "author": null, "contributor": null}, {"id": "concept_django_redis", "label": "django-redis (Django cache backend)", "file_type": "concept", "source_file": "backend/requirements-base.txt", "source_location": null, "source_url": null, "captured_at": null, "author": null, "contributor": null}, {"id": "concept_django_filter", "label": "django-filter (queryset filtering)", "file_type": "concept", "source_file": "backend/requirements-base.txt", "source_location": null, "source_url": null, "captured_at": null, "author": null, "contributor": null}, {"id": "concept_feedparser", "label": "feedparser (RSS/Atom feed parser)", "file_type": "concept", "source_file": "backend/requirements-base.txt", "source_location": null, "source_url": null, "captured_at": null, "author": null, "contributor": null}, {"id": "concept_requests", "label": "requests (HTTP client)", "file_type": "concept", "source_file": "backend/requirements-base.txt", "source_location": null, "source_url": null, "captured_at": null, "author": null, "contributor": null}, {"id": "concept_urllib3", "label": "urllib3 (HTTP client low-level)", "file_type": "concept", "source_file": "backend/requirements-base.txt", "source_location": null, "source_url": null, "captured_at": null, "author": null, "contributor": null}, {"id": "concept_zipp", "label": "zipp (zipfile backport)", "file_type": "concept", "source_file": "backend/requirements-base.txt", "source_location": null, "source_url": null, "captured_at": null, "author": null, "contributor": null}], "edges": [{"source": "backend_requirements_base", "target": "concept_django", "relation": "references", "confidence": "EXTRACTED", "confidence_score": 1.0, "source_file": "backend/requirements-base.txt", "source_location": null, "weight": 1.0}, {"source": "backend_requirements_base", "target": "concept_drf", "relation": "references", "confidence": "EXTRACTED", "confidence_score": 1.0, "source_file": "backend/requirements-base.txt", "source_location": null, "weight": 1.0}, {"source": "backend_requirements_base", "target": "concept_simplejwt", "relation": "references", "confidence": "EXTRACTED", "confidence_score": 1.0, "source_file": "backend/requirements-base.txt", "source_location": null, "weight": 1.0}, {"source": "backend_requirements_base", "target": "concept_django_cors_headers", "relation": "references", "confidence": "EXTRACTED", "confidence_score": 1.0, "source_file": "backend/requirements-base.txt", "source_location": null, "weight": 1.0}, {"source": "backend_requirements_base", "target": "concept_celery", "relation": "references", "confidence": "EXTRACTED", "confidence_score": 1.0, "source_file": "backend/requirements-base.txt", "source_location": null, "weight": 1.0}, {"source": "backend_requirements_base", "target": "concept_redis", "relation": "references", "confidence": "EXTRACTED", "confidence_score": 1.0, "source_file": "backend/requirements-base.txt", "source_location": null, "weight": 1.0}, {"source": "backend_requirements_base", "target": "concept_gunicorn", "relation": "references", "confidence": "EXTRACTED", "confidence_score": 1.0, "source_file": "backend/requirements-base.txt", "source_location": null, "weight": 1.0}, {"source": "backend_requirements_base", "target": "concept_uvicorn", "relation": "references", "confidence": "EXTRACTED", "confidence_score": 1.0, "source_file": "backend/requirements-base.txt", "source_location": null, "weight": 1.0}, {"source": "backend_requirements_base", "target": "concept_django_environ", "relation": "references", "confidence": "EXTRACTED", "confidence_score": 1.0, "source_file": "backend/requirements-base.txt", "source_location": null, "weight": 1.0}, {"source": "backend_requirements_base", "target": "concept_django_redis", "relation": "references", "confidence": "EXTRACTED", "confidence_score": 1.0, "source_file": "backend/requirements-base.txt", "source_location": null, "weight": 1.0}, {"source": "backend_requirements_base", "target": "concept_django_filter", "relation": "references", "confidence": "EXTRACTED", "confidence_score": 1.0, "source_file": "backend/requirements-base.txt", "source_location": null, "weight": 1.0}, {"source": "backend_requirements_base", "target": "concept_feedparser", "relation": "references", "confidence": "EXTRACTED", "confidence_score": 1.0, "source_file": "backend/requirements-base.txt", "source_location": null, "weight": 1.0}, {"source": "backend_requirements_base", "target": "concept_requests", "relation": "references", "confidence": "EXTRACTED", "confidence_score": 1.0, "source_file": "backend/requirements-base.txt", "source_location": null, "weight": 1.0}, {"source": "backend_requirements_base", "target": "concept_urllib3", "relation": "references", "confidence": "EXTRACTED", "confidence_score": 1.0, "source_file": "backend/requirements-base.txt", "source_location": null, "weight": 1.0}, {"source": "backend_requirements_base", "target": "concept_zipp", "relation": "references", "confidence": "EXTRACTED", "confidence_score": 1.0, "source_file": "backend/requirements-base.txt", "source_location": null, "weight": 1.0}, {"source": "concept_django_redis", "target": "concept_redis", "relation": "implements", "confidence": "EXTRACTED", "confidence_score": 1.0, "source_file": "backend/requirements-base.txt", "source_location": null, "weight": 1.0}, {"source": "concept_uvicorn", "target": "concept_django", "relation": "implements", "confidence": "INFERRED", "confidence_score": 0.65, "source_file": "backend/requirements-base.txt", "source_location": null, "weight": 1.0}, {"source": "concept_uvicorn", "target": "concept_gunicorn", "relation": "conceptually_related_to", "confidence": "INFERRED", "confidence_score": 0.75, "source_file": "backend/requirements-base.txt", "source_location": null, "weight": 1.0}, {"source": "concept_uvicorn", "target": "concept_gunicorn", "relation": "semantically_similar_to", "confidence": "INFERRED", "confidence_score": 0.75, "source_file": "backend/requirements-base.txt", "source_location": null, "weight": 1.0}, {"source": "concept_feedparser", "target": "concept_django", "relation": "conceptually_related_to", "confidence": "INFERRED", "confidence_score": 0.85, "source_file": "backend/requirements-base.txt", "source_location": null, "weight": 1.0}], "hyperedges": []}