{"nodes": [{"id": "podigger_docker_compose_local", "label": "Local Docker Compose (Postgres + Redis only)", "file_type": "code", "source_file": "docker-compose.local.yml", "source_location": null, "source_url": null, "captured_at": null, "author": null, "contributor": null}, {"id": "rationale_local_compose_split", "label": "WHY docker-compose.local.yml is infra-only: local dev uses UV-managed Python venv for app code, only Postgres+Redis run in containers", "file_type": "rationale", "source_file": "docker-compose.local.yml", "source_location": null, "source_url": null, "captured_at": null, "author": null, "contributor": null}], "edges": [{"source": "podigger_docker_compose_local", "target": "concept_postgres", "relation": "references", "confidence": "EXTRACTED", "confidence_score": 1.0, "source_file": "docker-compose.local.yml", "source_location": null, "weight": 1.0}, {"source": "podigger_docker_compose_local", "target": "concept_redis", "relation": "references", "confidence": "EXTRACTED", "confidence_score": 1.0, "source_file": "docker-compose.local.yml", "source_location": null, "weight": 1.0}, {"source": "rationale_local_compose_split", "target": "podigger_docker_compose_local", "relation": "rationale_for", "confidence": "EXTRACTED", "confidence_score": 1.0, "source_file": "docker-compose.local.yml", "source_location": null, "weight": 1.0}], "hyperedges": []}