{"nodes": [{"id": "home_perna_workspace_projects_podigger_backend_podcasts_views_py", "label": "views.py", "file_type": "code", "source_file": "backend/podcasts/views.py", "source_location": "L1"}, {"id": "podcasts_views_podcastpagination", "label": "PodcastPagination", "file_type": "code", "source_file": "backend/podcasts/views.py", "source_location": "L28"}, {"id": "pagenumberpagination", "label": "PageNumberPagination", "file_type": "code", "source_file": "", "source_location": ""}, {"id": "podcasts_views_podcastviewset", "label": "PodcastViewSet", "file_type": "code", "source_file": "backend/podcasts/views.py", "source_location": "L36"}, {"id": "podcasts_views_podcastviewset_get_queryset", "label": ".get_queryset()", "file_type": "code", "source_file": "backend/podcasts/views.py", "source_location": "L53"}, {"id": "podcasts_views_podcastviewset_get_permissions", "label": ".get_permissions()", "file_type": "code", "source_file": "backend/podcasts/views.py", "source_location": "L71"}, {"id": "podcasts_views_podcastviewset_get_serializer_class", "label": ".get_serializer_class()", "file_type": "code", "source_file": "backend/podcasts/views.py", "source_location": "L77"}, {"id": "podcasts_views_podcastviewset_create", "label": ".create()", "file_type": "code", "source_file": "backend/podcasts/views.py", "source_location": "L83"}, {"id": "podcasts_views_podcastviewset_recent", "label": ".recent()", "file_type": "code", "source_file": "backend/podcasts/views.py", "source_location": "L123"}, {"id": "podcasts_views_episodeviewset", "label": "EpisodeViewSet", "file_type": "code", "source_file": "backend/podcasts/views.py", "source_location": "L136"}, {"id": "podcasts_views_episodeviewset_get_permissions", "label": ".get_permissions()", "file_type": "code", "source_file": "backend/podcasts/views.py", "source_location": "L147"}, {"id": "podcasts_views_episodeviewset_get_queryset", "label": ".get_queryset()", "file_type": "code", "source_file": "backend/podcasts/views.py", "source_location": "L153"}, {"id": "podcasts_views_podcastlanguageviewset", "label": "PodcastLanguageViewSet", "file_type": "code", "source_file": "backend/podcasts/views.py", "source_location": "L187"}, {"id": "podcasts_views_topicsuggestionviewset", "label": "TopicSuggestionViewSet", "file_type": "code", "source_file": "backend/podcasts/views.py", "source_location": "L196"}, {"id": "podcasts_views_topicsuggestionviewset_get_permissions", "label": ".get_permissions()", "file_type": "code", "source_file": "backend/podcasts/views.py", "source_location": "L202"}, {"id": "podcasts_views_populartermviewset", "label": "PopularTermViewSet", "file_type": "code", "source_file": "backend/podcasts/views.py", "source_location": "L209"}, {"id": "podcasts_views_rationale_29", "label": "Pagination for podcasts with page_size=20 (T010).", "file_type": "rationale", "source_file": "backend/podcasts/views.py", "source_location": "L29"}, {"id": "podcasts_views_rationale_37", "label": "ViewSet for viewing and creating Podcasts.      Queryset shape (US3, FR-005, FR-", "file_type": "rationale", "source_file": "backend/podcasts/views.py", "source_location": "L37"}, {"id": "podcasts_views_rationale_54", "label": "Return the queryset, with eager loading tuned for each action.          - `list`", "file_type": "rationale", "source_file": "backend/podcasts/views.py", "source_location": "L54"}, {"id": "podcasts_views_rationale_72", "label": "Return AllowAny for read actions; require IsEditorOrAdmin for writes.", "file_type": "rationale", "source_file": "backend/podcasts/views.py", "source_location": "L72"}, {"id": "podcasts_views_rationale_78", "label": "Return the serializer class based on the action.", "file_type": "rationale", "source_file": "backend/podcasts/views.py", "source_location": "L78"}, {"id": "podcasts_views_rationale_84", "label": "Create a Podcast from JSON request data and enqueue episode import.          Par", "file_type": "rationale", "source_file": "backend/podcasts/views.py", "source_location": "L84"}, {"id": "podcasts_views_rationale_124", "label": "Return the six most recently created podcasts.          Returns:             Res", "file_type": "rationale", "source_file": "backend/podcasts/views.py", "source_location": "L124"}, {"id": "podcasts_views_rationale_137", "label": "Episode viewset with PostgreSQL full-text search support.      Use `GET /api/epi", "file_type": "rationale", "source_file": "backend/podcasts/views.py", "source_location": "L137"}, {"id": "podcasts_views_rationale_148", "label": "Return AllowAny for read actions; require IsEditorOrAdmin for writes.", "file_type": "rationale", "source_file": "backend/podcasts/views.py", "source_location": "L148"}, {"id": "podcasts_views_rationale_154", "label": "Return the queryset, optionally filtered by search term.          Search path (w", "file_type": "rationale", "source_file": "backend/podcasts/views.py", "source_location": "L154"}, {"id": "podcasts_views_rationale_188", "label": "ViewSet for listing available podcast languages (T012).", "file_type": "rationale", "source_file": "backend/podcasts/views.py", "source_location": "L188"}, {"id": "podcasts_views_rationale_197", "label": "ViewSet for handling Topic Suggestions.", "file_type": "rationale", "source_file": "backend/podcasts/views.py", "source_location": "L197"}, {"id": "podcasts_views_rationale_203", "label": "Return AllowAny for read actions; require IsEditorOrAdmin for writes.", "file_type": "rationale", "source_file": "backend/podcasts/views.py", "source_location": "L203"}, {"id": "podcasts_views_rationale_210", "label": "ViewSet for viewing Popular Terms.", "file_type": "rationale", "source_file": "backend/podcasts/views.py", "source_location": "L210"}], "edges": [{"source": "home_perna_workspace_projects_podigger_backend_podcasts_views_py", "target": "typing", "relation": "imports_from", "context": "import", "confidence": "EXTRACTED", "source_file": "backend/podcasts/views.py", "source_location": "L1", "weight": 1.0}, {"source": "home_perna_workspace_projects_podigger_backend_podcasts_views_py", "target": "django_db_models", "relation": "imports_from", "context": "import", "confidence": "EXTRACTED", "source_file": "backend/podcasts/views.py", "source_location": "L3", "weight": 1.0}, {"source": "home_perna_workspace_projects_podigger_backend_podcasts_views_py", "target": "accounts_permissions", "relation": "imports_from", "context": "import", "confidence": "EXTRACTED", "source_file": "backend/podcasts/views.py", "source_location": "L5", "weight": 1.0}, {"source": "home_perna_workspace_projects_podigger_backend_podcasts_views_py", "target": "django_filters_rest_framework", "relation": "imports_from", "context": "import", "confidence": "EXTRACTED", "source_file": "backend/podcasts/views.py", "source_location": "L6", "weight": 1.0}, {"source": "home_perna_workspace_projects_podigger_backend_podcasts_views_py", "target": "rest_framework", "relation": "imports_from", "context": "import", "confidence": "EXTRACTED", "source_file": "backend/podcasts/views.py", "source_location": "L7", "weight": 1.0}, {"source": "home_perna_workspace_projects_podigger_backend_podcasts_views_py", "target": "rest_framework_decorators", "relation": "imports_from", "context": "import", "confidence": "EXTRACTED", "source_file": "backend/podcasts/views.py", "source_location": "L8", "weight": 1.0}, {"source": "home_perna_workspace_projects_podigger_backend_podcasts_views_py", "target": "rest_framework_pagination", "relation": "imports_from", "context": "import", "confidence": "EXTRACTED", "source_file": "backend/podcasts/views.py", "source_location": "L9", "weight": 1.0}, {"source": "home_perna_workspace_projects_podigger_backend_podcasts_views_py", "target": "rest_framework_permissions", "relation": "imports_from", "context": "import", "confidence": "EXTRACTED", "source_file": "backend/podcasts/views.py", "source_location": "L10", "weight": 1.0}, {"source": "home_perna_workspace_projects_podigger_backend_podcasts_views_py", "target": "rest_framework_response", "relation": "imports_from", "context": "import", "confidence": "EXTRACTED", "source_file": "backend/podcasts/views.py", "source_location": "L11", "weight": 1.0}, {"source": "home_perna_workspace_projects_podigger_backend_podcasts_views_py", "target": "home_perna_workspace_projects_podigger_backend_podcasts_models_py", "relation": "imports_from", "context": "import", "confidence": "EXTRACTED", "source_file": "backend/podcasts/views.py", "source_location": "L13", "weight": 1.0}, {"source": "home_perna_workspace_projects_podigger_backend_podcasts_views_py", "target": "home_perna_workspace_projects_podigger_backend_podcasts_serializers_py", "relation": "imports_from", "context": "import", "confidence": "EXTRACTED", "source_file": "backend/podcasts/views.py", "source_location": "L14", "weight": 1.0}, {"source": "home_perna_workspace_projects_podigger_backend_podcasts_views_py", "target": "home_perna_workspace_projects_podigger_backend_podcasts_services_podcast_service_py", "relation": "imports_from", "context": "import", "confidence": "EXTRACTED", "source_file": "backend/podcasts/views.py", "source_location": "L22", "weight": 1.0}, {"source": "home_perna_workspace_projects_podigger_backend_podcasts_views_py", "target": "home_perna_workspace_projects_podigger_backend_podcasts_tasks_py", "relation": "imports_from", "context": "import", "confidence": "EXTRACTED", "source_file": "backend/podcasts/views.py", "source_location": "L23", "weight": 1.0}, {"source": "home_perna_workspace_projects_podigger_backend_podcasts_views_py", "target": "podcasts_views_podcastpagination", "relation": "contains", "confidence": "EXTRACTED", "source_file": "backend/podcasts/views.py", "source_location": "L28", "weight": 1.0}, {"source": "podcasts_views_podcastpagination", "target": "pagenumberpagination", "relation": "inherits", "confidence": "EXTRACTED", "source_file": "backend/podcasts/views.py", "source_location": "L28", "weight": 1.0}, {"source": "home_perna_workspace_projects_podigger_backend_podcasts_views_py", "target": "podcasts_views_podcastviewset", "relation": "contains", "confidence": "EXTRACTED", "source_file": "backend/podcasts/views.py", "source_location": "L36", "weight": 1.0}, {"source": "podcasts_views_podcastviewset", "target": "podcasts_views_podcastviewset_get_queryset", "relation": "method", "confidence": "EXTRACTED", "source_file": "backend/podcasts/views.py", "source_location": "L53", "weight": 1.0}, {"source": "podcasts_views_podcastviewset", "target": "podcasts_views_podcastviewset_get_permissions", "relation": "method", "confidence": "EXTRACTED", "source_file": "backend/podcasts/views.py", "source_location": "L71", "weight": 1.0}, {"source": "podcasts_views_podcastviewset", "target": "podcasts_views_podcastviewset_get_serializer_class", "relation": "method", "confidence": "EXTRACTED", "source_file": "backend/podcasts/views.py", "source_location": "L77", "weight": 1.0}, {"source": "podcasts_views_podcastviewset", "target": "podcasts_views_podcastviewset_create", "relation": "method", "confidence": "EXTRACTED", "source_file": "backend/podcasts/views.py", "source_location": "L83", "weight": 1.0}, {"source": "podcasts_views_podcastviewset", "target": "podcasts_views_podcastviewset_recent", "relation": "method", "confidence": "EXTRACTED", "source_file": "backend/podcasts/views.py", "source_location": "L123", "weight": 1.0}, {"source": "home_perna_workspace_projects_podigger_backend_podcasts_views_py", "target": "podcasts_views_episodeviewset", "relation": "contains", "confidence": "EXTRACTED", "source_file": "backend/podcasts/views.py", "source_location": "L136", "weight": 1.0}, {"source": "podcasts_views_episodeviewset", "target": "podcasts_views_episodeviewset_get_permissions", "relation": "method", "confidence": "EXTRACTED", "source_file": "backend/podcasts/views.py", "source_location": "L147", "weight": 1.0}, {"source": "podcasts_views_episodeviewset", "target": "podcasts_views_episodeviewset_get_queryset", "relation": "method", "confidence": "EXTRACTED", "source_file": "backend/podcasts/views.py", "source_location": "L153", "weight": 1.0}, {"source": "home_perna_workspace_projects_podigger_backend_podcasts_views_py", "target": "podcasts_views_podcastlanguageviewset", "relation": "contains", "confidence": "EXTRACTED", "source_file": "backend/podcasts/views.py", "source_location": "L187", "weight": 1.0}, {"source": "home_perna_workspace_projects_podigger_backend_podcasts_views_py", "target": "podcasts_views_topicsuggestionviewset", "relation": "contains", "confidence": "EXTRACTED", "source_file": "backend/podcasts/views.py", "source_location": "L196", "weight": 1.0}, {"source": "podcasts_views_topicsuggestionviewset", "target": "podcasts_views_topicsuggestionviewset_get_permissions", "relation": "method", "confidence": "EXTRACTED", "source_file": "backend/podcasts/views.py", "source_location": "L202", "weight": 1.0}, {"source": "home_perna_workspace_projects_podigger_backend_podcasts_views_py", "target": "podcasts_views_populartermviewset", "relation": "contains", "confidence": "EXTRACTED", "source_file": "backend/podcasts/views.py", "source_location": "L209", "weight": 1.0}, {"source": "podcasts_views_podcastviewset_recent", "target": "podcasts_views_episodeviewset_get_queryset", "relation": "calls", "context": "call", "confidence": "EXTRACTED", "source_file": "backend/podcasts/views.py", "source_location": "L131", "weight": 1.0}, {"source": "podcasts_views_rationale_29", "target": "podcasts_views_podcastpagination", "relation": "rationale_for", "confidence": "EXTRACTED", "source_file": "backend/podcasts/views.py", "source_location": "L29", "weight": 1.0}, {"source": "podcasts_views_rationale_37", "target": "podcasts_views_podcastviewset", "relation": "rationale_for", "confidence": "EXTRACTED", "source_file": "backend/podcasts/views.py", "source_location": "L37", "weight": 1.0}, {"source": "podcasts_views_rationale_54", "target": "podcasts_views_podcastviewset_get_queryset", "relation": "rationale_for", "confidence": "EXTRACTED", "source_file": "backend/podcasts/views.py", "source_location": "L54", "weight": 1.0}, {"source": "podcasts_views_rationale_72", "target": "podcasts_views_podcastviewset_get_permissions", "relation": "rationale_for", "confidence": "EXTRACTED", "source_file": "backend/podcasts/views.py", "source_location": "L72", "weight": 1.0}, {"source": "podcasts_views_rationale_78", "target": "podcasts_views_podcastviewset_get_serializer_class", "relation": "rationale_for", "confidence": "EXTRACTED", "source_file": "backend/podcasts/views.py", "source_location": "L78", "weight": 1.0}, {"source": "podcasts_views_rationale_84", "target": "podcasts_views_podcastviewset_create", "relation": "rationale_for", "confidence": "EXTRACTED", "source_file": "backend/podcasts/views.py", "source_location": "L84", "weight": 1.0}, {"source": "podcasts_views_rationale_124", "target": "podcasts_views_podcastviewset_recent", "relation": "rationale_for", "confidence": "EXTRACTED", "source_file": "backend/podcasts/views.py", "source_location": "L124", "weight": 1.0}, {"source": "podcasts_views_rationale_137", "target": "podcasts_views_episodeviewset", "relation": "rationale_for", "confidence": "EXTRACTED", "source_file": "backend/podcasts/views.py", "source_location": "L137", "weight": 1.0}, {"source": "podcasts_views_rationale_148", "target": "podcasts_views_episodeviewset_get_permissions", "relation": "rationale_for", "confidence": "EXTRACTED", "source_file": "backend/podcasts/views.py", "source_location": "L148", "weight": 1.0}, {"source": "podcasts_views_rationale_154", "target": "podcasts_views_episodeviewset_get_queryset", "relation": "rationale_for", "confidence": "EXTRACTED", "source_file": "backend/podcasts/views.py", "source_location": "L154", "weight": 1.0}, {"source": "podcasts_views_rationale_188", "target": "podcasts_views_podcastlanguageviewset", "relation": "rationale_for", "confidence": "EXTRACTED", "source_file": "backend/podcasts/views.py", "source_location": "L188", "weight": 1.0}, {"source": "podcasts_views_rationale_197", "target": "podcasts_views_topicsuggestionviewset", "relation": "rationale_for", "confidence": "EXTRACTED", "source_file": "backend/podcasts/views.py", "source_location": "L197", "weight": 1.0}, {"source": "podcasts_views_rationale_203", "target": "podcasts_views_topicsuggestionviewset_get_permissions", "relation": "rationale_for", "confidence": "EXTRACTED", "source_file": "backend/podcasts/views.py", "source_location": "L203", "weight": 1.0}, {"source": "podcasts_views_rationale_210", "target": "podcasts_views_populartermviewset", "relation": "rationale_for", "confidence": "EXTRACTED", "source_file": "backend/podcasts/views.py", "source_location": "L210", "weight": 1.0}], "raw_calls": [{"caller_nid": "podcasts_views_podcastviewset_get_queryset", "callee": "order_by", "is_member_call": true, "source_file": "/home/perna/workspace/projects/podigger/backend/podcasts/views.py", "source_location": "L59", "receiver": null}, {"caller_nid": "podcasts_views_podcastviewset_get_queryset", "callee": "select_related", "is_member_call": true, "source_file": "/home/perna/workspace/projects/podigger/backend/podcasts/views.py", "source_location": "L59", "receiver": null}, {"caller_nid": "podcasts_views_podcastviewset_get_queryset", "callee": "prefetch_related", "is_member_call": true, "source_file": "/home/perna/workspace/projects/podigger/backend/podcasts/views.py", "source_location": "L61", "receiver": "qs"}, {"caller_nid": "podcasts_views_podcastviewset_get_queryset", "callee": "Prefetch", "is_member_call": false, "source_file": "/home/perna/workspace/projects/podigger/backend/podcasts/views.py", "source_location": "L62", "receiver": null}, {"caller_nid": "podcasts_views_podcastviewset_get_queryset", "callee": "order_by", "is_member_call": true, "source_file": "/home/perna/workspace/projects/podigger/backend/podcasts/views.py", "source_location": "L64", "receiver": null}, {"caller_nid": "podcasts_views_podcastviewset_get_queryset", "callee": "prefetch_related", "is_member_call": true, "source_file": "/home/perna/workspace/projects/podigger/backend/podcasts/views.py", "source_location": "L64", "receiver": null}, {"caller_nid": "podcasts_views_podcastviewset_get_queryset", "callee": "select_related", "is_member_call": true, "source_file": "/home/perna/workspace/projects/podigger/backend/podcasts/views.py", "source_location": "L64", "receiver": null}, {"caller_nid": "podcasts_views_podcastviewset_get_permissions", "callee": "AllowAny", "is_member_call": false, "source_file": "/home/perna/workspace/projects/podigger/backend/podcasts/views.py", "source_location": "L74", "receiver": null}, {"caller_nid": "podcasts_views_podcastviewset_get_permissions", "callee": "IsEditorOrAdmin", "is_member_call": false, "source_file": "/home/perna/workspace/projects/podigger/backend/podcasts/views.py", "source_location": "L75", "receiver": null}, {"caller_nid": "podcasts_views_podcastviewset_create", "callee": "create_podcast", "is_member_call": true, "source_file": "/home/perna/workspace/projects/podigger/backend/podcasts/views.py", "source_location": "L98", "receiver": "PodcastService"}, {"caller_nid": "podcasts_views_podcastviewset_create", "callee": "get", "is_member_call": true, "source_file": "/home/perna/workspace/projects/podigger/backend/podcasts/views.py", "source_location": "L99", "receiver": null}, {"caller_nid": "podcasts_views_podcastviewset_create", "callee": "get", "is_member_call": true, "source_file": "/home/perna/workspace/projects/podigger/backend/podcasts/views.py", "source_location": "L99", "receiver": null}, {"caller_nid": "podcasts_views_podcastviewset_recent", "callee": "PodcastListSerializer", "is_member_call": false, "source_file": "/home/perna/workspace/projects/podigger/backend/podcasts/views.py", "source_location": "L132", "receiver": null}, {"caller_nid": "podcasts_views_episodeviewset_get_permissions", "callee": "AllowAny", "is_member_call": false, "source_file": "/home/perna/workspace/projects/podigger/backend/podcasts/views.py", "source_location": "L150", "receiver": null}, {"caller_nid": "podcasts_views_episodeviewset_get_permissions", "callee": "IsEditorOrAdmin", "is_member_call": false, "source_file": "/home/perna/workspace/projects/podigger/backend/podcasts/views.py", "source_location": "L151", "receiver": null}, {"caller_nid": "podcasts_views_episodeviewset_get_queryset", "callee": "prefetch_related", "is_member_call": true, "source_file": "/home/perna/workspace/projects/podigger/backend/podcasts/views.py", "source_location": "L167", "receiver": null}, {"caller_nid": "podcasts_views_episodeviewset_get_queryset", "callee": "select_related", "is_member_call": true, "source_file": "/home/perna/workspace/projects/podigger/backend/podcasts/views.py", "source_location": "L167", "receiver": null}, {"caller_nid": "podcasts_views_episodeviewset_get_queryset", "callee": "get", "is_member_call": true, "source_file": "/home/perna/workspace/projects/podigger/backend/podcasts/views.py", "source_location": "L168", "receiver": null}, {"caller_nid": "podcasts_views_episodeviewset_get_queryset", "callee": "get", "is_member_call": true, "source_file": "/home/perna/workspace/projects/podigger/backend/podcasts/views.py", "source_location": "L168", "receiver": null}, {"caller_nid": "podcasts_views_episodeviewset_get_queryset", "callee": "prefetch_related", "is_member_call": true, "source_file": "/home/perna/workspace/projects/podigger/backend/podcasts/views.py", "source_location": "L174", "receiver": null}, {"caller_nid": "podcasts_views_episodeviewset_get_queryset", "callee": "select_related", "is_member_call": true, "source_file": "/home/perna/workspace/projects/podigger/backend/podcasts/views.py", "source_location": "L174", "receiver": null}, {"caller_nid": "podcasts_views_episodeviewset_get_queryset", "callee": "search", "is_member_call": true, "source_file": "/home/perna/workspace/projects/podigger/backend/podcasts/views.py", "source_location": "L174", "receiver": null}, {"caller_nid": "podcasts_views_episodeviewset_get_queryset", "callee": "delay", "is_member_call": true, "source_file": "/home/perna/workspace/projects/podigger/backend/podcasts/views.py", "source_location": "L181", "receiver": "record_search_term"}, {"caller_nid": "podcasts_views_topicsuggestionviewset_get_permissions", "callee": "AllowAny", "is_member_call": false, "source_file": "/home/perna/workspace/projects/podigger/backend/podcasts/views.py", "source_location": "L205", "receiver": null}, {"caller_nid": "podcasts_views_topicsuggestionviewset_get_permissions", "callee": "IsEditorOrAdmin", "is_member_call": false, "source_file": "/home/perna/workspace/projects/podigger/backend/podcasts/views.py", "source_location": "L206", "receiver": null}]}