{"nodes": [{"id": "home_perna_workspace_projects_podigger_changelog_md", "label": "CHANGELOG.md", "file_type": "document", "source_file": "CHANGELOG.md", "source_location": "L1"}, {"id": "podigger_changelog_changelog", "label": "Changelog", "file_type": "document", "source_file": "CHANGELOG.md", "source_location": "L1"}, {"id": "podigger_changelog_unreleased", "label": "[Unreleased]", "file_type": "document", "source_file": "CHANGELOG.md", "source_location": "L8"}, {"id": "podigger_changelog_added", "label": "Added", "file_type": "document", "source_file": "CHANGELOG.md", "source_location": "L10"}, {"id": "podigger_changelog_changed", "label": "Changed", "file_type": "document", "source_file": "CHANGELOG.md", "source_location": "L38"}, {"id": "podigger_changelog_performance", "label": "Performance", "file_type": "document", "source_file": "CHANGELOG.md", "source_location": "L45"}, {"id": "podigger_changelog_fixed", "label": "Fixed", "file_type": "document", "source_file": "CHANGELOG.md", "source_location": "L52"}, {"id": "podigger_changelog_2_1_0_2026_02_28", "label": "[2.1.0] - 2026-02-28", "file_type": "document", "source_file": "CHANGELOG.md", "source_location": "L61"}, {"id": "podigger_changelog_added_63", "label": "Added", "file_type": "document", "source_file": "CHANGELOG.md", "source_location": "L63"}, {"id": "podigger_changelog_fixed_75", "label": "Fixed", "file_type": "document", "source_file": "CHANGELOG.md", "source_location": "L75"}, {"id": "podigger_changelog_changed_80", "label": "Changed", "file_type": "document", "source_file": "CHANGELOG.md", "source_location": "L80"}, {"id": "podigger_changelog_fixed_88", "label": "Fixed", "file_type": "document", "source_file": "CHANGELOG.md", "source_location": "L88"}, {"id": "podigger_changelog_legacy_versions", "label": "Legacy Versions", "file_type": "document", "source_file": "CHANGELOG.md", "source_location": "L96"}, {"id": "podigger_changelog_0_3_0_2016_09_19", "label": "[0.3.0] - 2016-09-19", "file_type": "document", "source_file": "CHANGELOG.md", "source_location": "L100"}, {"id": "podigger_changelog_added_102", "label": "Added", "file_type": "document", "source_file": "CHANGELOG.md", "source_location": "L102"}, {"id": "podigger_changelog_changed_107", "label": "Changed", "file_type": "document", "source_file": "CHANGELOG.md", "source_location": "L107"}, {"id": "podigger_changelog_fixed_110", "label": "Fixed", "file_type": "document", "source_file": "CHANGELOG.md", "source_location": "L110"}, {"id": "podigger_changelog_0_2_6_2016_09_08", "label": "[0.2.6] - 2016-09-08", "file_type": "document", "source_file": "CHANGELOG.md", "source_location": "L113"}, {"id": "podigger_changelog_fixed_115", "label": "Fixed", "file_type": "document", "source_file": "CHANGELOG.md", "source_location": "L115"}, {"id": "podigger_changelog_removed", "label": "Removed", "file_type": "document", "source_file": "CHANGELOG.md", "source_location": "L118"}, {"id": "podigger_changelog_0_2_5_2016_09_08", "label": "[0.2.5] - 2016-09-08", "file_type": "document", "source_file": "CHANGELOG.md", "source_location": "L121"}, {"id": "podigger_changelog_fixed_123", "label": "Fixed", "file_type": "document", "source_file": "CHANGELOG.md", "source_location": "L123"}, {"id": "podigger_changelog_changed_127", "label": "Changed", "file_type": "document", "source_file": "CHANGELOG.md", "source_location": "L127"}, {"id": "podigger_changelog_0_2_4_2016_07_31", "label": "[0.2.4] - 2016-07-31", "file_type": "document", "source_file": "CHANGELOG.md", "source_location": "L132"}, {"id": "podigger_changelog_changed_134", "label": "Changed", "file_type": "document", "source_file": "CHANGELOG.md", "source_location": "L134"}, {"id": "podigger_changelog_0_2_3_2014_06_30", "label": "[0.2.3] - 2014-06-30", "file_type": "document", "source_file": "CHANGELOG.md", "source_location": "L138"}, {"id": "podigger_changelog_added_140", "label": "Added", "file_type": "document", "source_file": "CHANGELOG.md", "source_location": "L140"}, {"id": "podigger_changelog_fixed_144", "label": "Fixed", "file_type": "document", "source_file": "CHANGELOG.md", "source_location": "L144"}, {"id": "podigger_changelog_0_1_2_2016_07_27", "label": "[0.1.2] - 2016-07-27", "file_type": "document", "source_file": "CHANGELOG.md", "source_location": "L147"}, {"id": "podigger_changelog_added_149", "label": "Added", "file_type": "document", "source_file": "CHANGELOG.md", "source_location": "L149"}, {"id": "podigger_changelog_changed_156", "label": "Changed", "file_type": "document", "source_file": "CHANGELOG.md", "source_location": "L156"}, {"id": "podigger_changelog_fixed_163", "label": "Fixed", "file_type": "document", "source_file": "CHANGELOG.md", "source_location": "L163"}, {"id": "podigger_changelog_removed_166", "label": "Removed", "file_type": "document", "source_file": "CHANGELOG.md", "source_location": "L166"}, {"id": "podigger_changelog_0_0_1_2016_06_19", "label": "[0.0.1] - 2016-06-19", "file_type": "document", "source_file": "CHANGELOG.md", "source_location": "L169"}], "edges": [{"source": "home_perna_workspace_projects_podigger_changelog_md", "target": "podigger_changelog_changelog", "relation": "contains", "confidence": "EXTRACTED", "source_file": "CHANGELOG.md", "source_location": "L1", "weight": 1.0}, {"source": "podigger_changelog_changelog", "target": "podigger_changelog_unreleased", "relation": "contains", "confidence": "EXTRACTED", "source_file": "CHANGELOG.md", "source_location": "L8", "weight": 1.0}, {"source": "podigger_changelog_unreleased", "target": "podigger_changelog_added", "relation": "contains", "confidence": "EXTRACTED", "source_file": "CHANGELOG.md", "source_location": "L10", "weight": 1.0}, {"source": "podigger_changelog_unreleased", "target": "podigger_changelog_changed", "relation": "contains", "confidence": "EXTRACTED", "source_file": "CHANGELOG.md", "source_location": "L38", "weight": 1.0}, {"source": "podigger_changelog_unreleased", "target": "podigger_changelog_performance", "relation": "contains", "confidence": "EXTRACTED", "source_file": "CHANGELOG.md", "source_location": "L45", "weight": 1.0}, {"source": "podigger_changelog_unreleased", "target": "podigger_changelog_fixed", "relation": "contains", "confidence": "EXTRACTED", "source_file": "CHANGELOG.md", "source_location": "L52", "weight": 1.0}, {"source": "podigger_changelog_changelog", "target": "podigger_changelog_2_1_0_2026_02_28", "relation": "contains", "confidence": "EXTRACTED", "source_file": "CHANGELOG.md", "source_location": "L61", "weight": 1.0}, {"source": "podigger_changelog_2_1_0_2026_02_28", "target": "podigger_changelog_added_63", "relation": "contains", "confidence": "EXTRACTED", "source_file": "CHANGELOG.md", "source_location": "L63", "weight": 1.0}, {"source": "podigger_changelog_2_1_0_2026_02_28", "target": "podigger_changelog_fixed_75", "relation": "contains", "confidence": "EXTRACTED", "source_file": "CHANGELOG.md", "source_location": "L75", "weight": 1.0}, {"source": "podigger_changelog_2_1_0_2026_02_28", "target": "podigger_changelog_changed_80", "relation": "contains", "confidence": "EXTRACTED", "source_file": "CHANGELOG.md", "source_location": "L80", "weight": 1.0}, {"source": "podigger_changelog_2_1_0_2026_02_28", "target": "podigger_changelog_fixed_88", "relation": "contains", "confidence": "EXTRACTED", "source_file": "CHANGELOG.md", "source_location": "L88", "weight": 1.0}, {"source": "podigger_changelog_changelog", "target": "podigger_changelog_legacy_versions", "relation": "contains", "confidence": "EXTRACTED", "source_file": "CHANGELOG.md", "source_location": "L96", "weight": 1.0}, {"source": "podigger_changelog_legacy_versions", "target": "podigger_changelog_0_3_0_2016_09_19", "relation": "contains", "confidence": "EXTRACTED", "source_file": "CHANGELOG.md", "source_location": "L100", "weight": 1.0}, {"source": "podigger_changelog_0_3_0_2016_09_19", "target": "podigger_changelog_added_102", "relation": "contains", "confidence": "EXTRACTED", "source_file": "CHANGELOG.md", "source_location": "L102", "weight": 1.0}, {"source": "podigger_changelog_0_3_0_2016_09_19", "target": "podigger_changelog_changed_107", "relation": "contains", "confidence": "EXTRACTED", "source_file": "CHANGELOG.md", "source_location": "L107", "weight": 1.0}, {"source": "podigger_changelog_0_3_0_2016_09_19", "target": "podigger_changelog_fixed_110", "relation": "contains", "confidence": "EXTRACTED", "source_file": "CHANGELOG.md", "source_location": "L110", "weight": 1.0}, {"source": "podigger_changelog_legacy_versions", "target": "podigger_changelog_0_2_6_2016_09_08", "relation": "contains", "confidence": "EXTRACTED", "source_file": "CHANGELOG.md", "source_location": "L113", "weight": 1.0}, {"source": "podigger_changelog_0_2_6_2016_09_08", "target": "podigger_changelog_fixed_115", "relation": "contains", "confidence": "EXTRACTED", "source_file": "CHANGELOG.md", "source_location": "L115", "weight": 1.0}, {"source": "podigger_changelog_0_2_6_2016_09_08", "target": "podigger_changelog_removed", "relation": "contains", "confidence": "EXTRACTED", "source_file": "CHANGELOG.md", "source_location": "L118", "weight": 1.0}, {"source": "podigger_changelog_legacy_versions", "target": "podigger_changelog_0_2_5_2016_09_08", "relation": "contains", "confidence": "EXTRACTED", "source_file": "CHANGELOG.md", "source_location": "L121", "weight": 1.0}, {"source": "podigger_changelog_0_2_5_2016_09_08", "target": "podigger_changelog_fixed_123", "relation": "contains", "confidence": "EXTRACTED", "source_file": "CHANGELOG.md", "source_location": "L123", "weight": 1.0}, {"source": "podigger_changelog_0_2_5_2016_09_08", "target": "podigger_changelog_changed_127", "relation": "contains", "confidence": "EXTRACTED", "source_file": "CHANGELOG.md", "source_location": "L127", "weight": 1.0}, {"source": "podigger_changelog_legacy_versions", "target": "podigger_changelog_0_2_4_2016_07_31", "relation": "contains", "confidence": "EXTRACTED", "source_file": "CHANGELOG.md", "source_location": "L132", "weight": 1.0}, {"source": "podigger_changelog_0_2_4_2016_07_31", "target": "podigger_changelog_changed_134", "relation": "contains", "confidence": "EXTRACTED", "source_file": "CHANGELOG.md", "source_location": "L134", "weight": 1.0}, {"source": "podigger_changelog_legacy_versions", "target": "podigger_changelog_0_2_3_2014_06_30", "relation": "contains", "confidence": "EXTRACTED", "source_file": "CHANGELOG.md", "source_location": "L138", "weight": 1.0}, {"source": "podigger_changelog_0_2_3_2014_06_30", "target": "podigger_changelog_added_140", "relation": "contains", "confidence": "EXTRACTED", "source_file": "CHANGELOG.md", "source_location": "L140", "weight": 1.0}, {"source": "podigger_changelog_0_2_3_2014_06_30", "target": "podigger_changelog_fixed_144", "relation": "contains", "confidence": "EXTRACTED", "source_file": "CHANGELOG.md", "source_location": "L144", "weight": 1.0}, {"source": "podigger_changelog_legacy_versions", "target": "podigger_changelog_0_1_2_2016_07_27", "relation": "contains", "confidence": "EXTRACTED", "source_file": "CHANGELOG.md", "source_location": "L147", "weight": 1.0}, {"source": "podigger_changelog_0_1_2_2016_07_27", "target": "podigger_changelog_added_149", "relation": "contains", "confidence": "EXTRACTED", "source_file": "CHANGELOG.md", "source_location": "L149", "weight": 1.0}, {"source": "podigger_changelog_0_1_2_2016_07_27", "target": "podigger_changelog_changed_156", "relation": "contains", "confidence": "EXTRACTED", "source_file": "CHANGELOG.md", "source_location": "L156", "weight": 1.0}, {"source": "podigger_changelog_0_1_2_2016_07_27", "target": "podigger_changelog_fixed_163", "relation": "contains", "confidence": "EXTRACTED", "source_file": "CHANGELOG.md", "source_location": "L163", "weight": 1.0}, {"source": "podigger_changelog_0_1_2_2016_07_27", "target": "podigger_changelog_removed_166", "relation": "contains", "confidence": "EXTRACTED", "source_file": "CHANGELOG.md", "source_location": "L166", "weight": 1.0}, {"source": "podigger_changelog_legacy_versions", "target": "podigger_changelog_0_0_1_2016_06_19", "relation": "contains", "confidence": "EXTRACTED", "source_file": "CHANGELOG.md", "source_location": "L169", "weight": 1.0}], "input_tokens": 0, "output_tokens": 0}